LICENSE
MANIFEST.in
README.md
pyproject.toml
setup.cfg
setup.py
docassemble.LAWVSolidFoundations.egg-info/PKG-INFO
docassemble.LAWVSolidFoundations.egg-info/SOURCES.txt
docassemble.LAWVSolidFoundations.egg-info/dependency_links.txt
docassemble.LAWVSolidFoundations.egg-info/not-zip-safe
docassemble.LAWVSolidFoundations.egg-info/top_level.txt
docassemble/LAWVSolidFoundations/__init__.py
docassemble/LAWVSolidFoundations/data/questions/adoption-questions.yml
docassemble/LAWVSolidFoundations/data/questions/generic-questions.yml
docassemble/LAWVSolidFoundations/data/questions/guardianship-questions.yml
docassemble/LAWVSolidFoundations/data/questions/solid-foundations.yml
docassemble/LAWVSolidFoundations/data/questions/will-clinic.yml
docassemble/LAWVSolidFoundations/data/sources/README.md
docassemble/LAWVSolidFoundations/data/static/README.md
docassemble/LAWVSolidFoundations/data/static/adoption.png
docassemble/LAWVSolidFoundations/data/static/bootstrap.min.css
docassemble/LAWVSolidFoundations/data/static/circle-icon-court1x.svg
docassemble/LAWVSolidFoundations/data/static/circle-icon-doc1x.svg
docassemble/LAWVSolidFoundations/data/static/circle-icon-id1x.svg
docassemble/LAWVSolidFoundations/data/static/circle-icon-print1x.svg
docassemble/LAWVSolidFoundations/data/static/circle-icon-time1x.svg
docassemble/LAWVSolidFoundations/data/static/diy.png
docassemble/LAWVSolidFoundations/data/static/download.png
docassemble/LAWVSolidFoundations/data/static/force_lightmode.js
docassemble/LAWVSolidFoundations/data/static/guardianship.png
docassemble/LAWVSolidFoundations/data/static/guided-questions.png
docassemble/LAWVSolidFoundations/data/static/icon-bank1x.svg
docassemble/LAWVSolidFoundations/data/static/icon-clock.png
docassemble/LAWVSolidFoundations/data/static/icon-clock1x.svg
docassemble/LAWVSolidFoundations/data/static/icon-cost.png
docassemble/LAWVSolidFoundations/data/static/icon-info1x.svg
docassemble/LAWVSolidFoundations/data/static/icon-kinship-caregivers.png
docassemble/LAWVSolidFoundations/data/static/icon-time.png
docassemble/LAWVSolidFoundations/data/static/icon-west-virginia.png
docassemble/LAWVSolidFoundations/data/static/kin.css
docassemble/LAWVSolidFoundations/data/static/progressivedisclosure.css
