Metadata-Version: 2.4
Name: docassemble.LAWVSolidFoundations
Version: 0.0.5
Summary: A docassemble extension.
Home-page: https://docassemble.org
Author: System Administrator
Author-email: dhenry@lawv.net
License: The MIT License (MIT)
License-File: LICENSE
Dynamic: author
Dynamic: author-email
Dynamic: description
Dynamic: description-content-type
Dynamic: home-page
Dynamic: license
Dynamic: license-file
Dynamic: summary
